LICENSE
MANIFEST.in
setup.py
django_hs_cache.egg-info/PKG-INFO
django_hs_cache.egg-info/SOURCES.txt
django_hs_cache.egg-info/dependency_links.txt
django_hs_cache.egg-info/requires.txt
django_hs_cache.egg-info/top_level.txt
hs_cache/__init__.py
hs_cache/handlersocket.py
tests/__init__.py
tests/manage.py
tests/settings.py
tests/cache_test/__init__.py
tests/cache_test/models.py
tests/cache_test/tests.py