Metadata-Version: 1.0
Name: django-hs-cache
Version: 0.1.2
Summary: HandlerSocket cache backend for Django
Home-page: http://bitbucket.org/dchaplinsky/django-hs-cache
Author: Dmitry Chaplinsky
Author-email: chaplinsky.dmitry@gmail.com
License: MIT
Platform: any
Classifier: Development Status :: 3 - Alpha
Classifier: Environment :: Console
Classifier: Environment :: Web Environment
Classifier: Intended Audience :: Developers
Classifier: License :: OSI Approved :: MIT License
Classifier: Operating System :: OS Independent
Classifier: Programming Language :: Python
Classifier: Topic :: Software Development :: Libraries
Classifier: Topic :: Database
Classifier: Framework :: Django
